filter_tabs/__init__.py
filter_tabs/extension.py
filter_tabs/renderer.py
filter_tabs/static/filter_tabs.css
sphinx_filter_tabs-1.2.6.dist-info/licenses/LICENSE
sphinx_filter_tabs-1.2.6.dist-info/METADATA
sphinx_filter_tabs-1.2.6.dist-info/WHEEL
sphinx_filter_tabs-1.2.6.dist-info/entry_points.txt
sphinx_filter_tabs-1.2.6.dist-info/top_level.txt
sphinx_filter_tabs-1.2.6.dist-info/RECORD
