Metadata-Version: 2.4
Name: sphinx-filter-tabs
Version: 1.2.6
Summary: A Sphinx extension for accessible, CSS-first filterable content tabs.
Author-email: Aputsiak Niels Janussen <aputtu+sphinx@gmail.com>
License: GNU General Public License v3.0
Project-URL: Homepage, https://github.com/aputtu/sphinx-filter-tabs
Project-URL: Repository, https://github.com/aputtu/sphinx-filter-tabs.git
Project-URL: Issues, https://github.com/aputtu/sphinx-filter-tabs/issues
Keywords: sphinx,extension,tabs,filter,documentation,css-only,accessibility,keyboard-navigation
Classifier: Development Status :: 5 - Production/Stable
Classifier: Framework :: Sphinx :: Extension
Classifier: Intended Audience :: Developers
Classifier: License :: OSI Approved :: GNU General Public License v3 (GPLv3)
Classifier: Operating System :: OS Independent
Classifier: Programming Language :: Python :: 3
Classifier: Programming Language :: Python :: 3.10
Classifier: Programming Language :: Python :: 3.12
Classifier: Topic :: Documentation :: Sphinx
Classifier: Topic :: Software Development :: Documentation
Requires-Python: >=3.10
License-File: LICENSE
Requires-Dist: Sphinx<9.0,>=7.0
Dynamic: license-file
